betting_env/__init__.py
betting_env/_modidx.py
betting_env/betting_env.py
betting_env/config/__init__.py
betting_env/config/localconfig.py
betting_env/config/mongo.py
betting_env/datastructure/__init__.py
betting_env/datastructure/fixtures.py
betting_env/datastructure/game_features.py
betting_env/datastructure/odds.py
betting_env/datastructure/team_lineup.py
betting_env/utils/__init__.py
betting_env/utils/asian_1x2_pnl.py
betting_env/utils/data_extractor.py
betting_env-0.1.0.dist-info/LICENSE
betting_env-0.1.0.dist-info/METADATA
betting_env-0.1.0.dist-info/WHEEL
betting_env-0.1.0.dist-info/entry_points.txt
betting_env-0.1.0.dist-info/top_level.txt
betting_env-0.1.0.dist-info/RECORD
